ebyst/__init__.py
ebyst/bsdl.py
ebyst/device.py
ebyst/staplay.py
ebyst/tap_controller.py
ebyst/trace.py
ebyst/drivers/__init__.py
ebyst/drivers/driver.py
ebyst/drivers/ftdi_mpsse.py
ebyst/drivers/sim.py
ebyst/interfaces/__init__.py
ebyst/interfaces/ddr3.py
ebyst/interfaces/ddr4.py
ebyst/interfaces/flash.py
ebyst/interfaces/hyperram.py
ebyst/interfaces/i2c.py
ebyst/interfaces/mdio.py
ebyst/interfaces/net.py
ebyst/interfaces/spi.py
ebyst/stapl/__init__.py
ebyst/stapl/aca.py
ebyst/stapl/data.py
ebyst/stapl/errors.py
ebyst/stapl/expressions.py
ebyst/stapl/interpreter.py
ebyst/stapl/stapl.py
ebyst-0.4.1.dist-info/METADATA
ebyst-0.4.1.dist-info/WHEEL
ebyst-0.4.1.dist-info/entry_points.txt
ebyst-0.4.1.dist-info/licenses/LICENSE
ebyst-0.4.1.dist-info/RECORD
