Metadata-Version: 2.4
Name: ebyst
Version: 0.4.1
Summary: Boundary scan test library
Project-URL: Homepage, https://github.com/swolix/ebyst
Project-URL: Issues, https://github.com/swolix/ebyst/issues
Author-email: Sijmen Woutersen <sijmen.woutersen@gmail.com>
License-File: LICENSE
Classifier: License :: OSI Approved :: MIT License
Classifier: Operating System :: OS Independent
Classifier: Programming Language :: Python :: 3
Requires-Python: >=3.8
Requires-Dist: bitarray==3.8.0
Requires-Dist: pyftdi==0.57.1
Requires-Dist: pyparsing==3.2.5
